cloudflare_exporter/__init__.py
cloudflare_exporter/cli.py
cloudflare_exporter/cloudflare_exporter.py
cloudflare_exporter/logging.py
cloudflare_exporter/metrics.py
cloudflare_exporter/gql/__init__.py
cloudflare_prometheus_exporter-0.3.10.dist-info/AUTHORS.md
cloudflare_prometheus_exporter-0.3.10.dist-info/LICENSE
cloudflare_prometheus_exporter-0.3.10.dist-info/METADATA
cloudflare_prometheus_exporter-0.3.10.dist-info/WHEEL
cloudflare_prometheus_exporter-0.3.10.dist-info/entry_points.txt
cloudflare_prometheus_exporter-0.3.10.dist-info/top_level.txt
cloudflare_prometheus_exporter-0.3.10.dist-info/RECORD
