Metadata-Version: 2.1
Name: cloudflare-prometheus-exporter
Version: 0.3.10
Summary: Prometheus exporter powered by Cloudflare GraphQL API.
Home-page: https://github.com/transferwise/cloudflare-exporter
Author: Wise::Observability
Author-email: observability@transferwise.com
License: Apache Software License 2.0
Keywords: cloudflare_exporter
Platform: UNKNOWN
Classifier: Development Status :: 2 - Pre-Alpha
Classifier: Intended Audience :: Developers
Classifier: License :: OSI Approved :: Apache Software License
Classifier: Natural Language :: English
Classifier: Programming Language :: Python :: 3
Classifier: Programming Language :: Python :: 3.4
Classifier: Programming Language :: Python :: 3.5
Classifier: Programming Language :: Python :: 3.6
Classifier: Programming Language :: Python :: 3.7
License-File: LICENSE
License-File: AUTHORS.md
Requires-Dist: click
Requires-Dist: requests
Requires-Dist: pyyaml
Requires-Dist: prometheus-client
Requires-Dist: python-json-logger
Requires-Dist: schedule
